README.md
setup.py
ObjectdetectionKeras/__init__.py
ObjectdetectionKeras.egg-info/PKG-INFO
ObjectdetectionKeras.egg-info/SOURCES.txt
ObjectdetectionKeras.egg-info/dependency_links.txt
ObjectdetectionKeras.egg-info/top_level.txt
ObjectdetectionKeras/Custom/__init__.py
ObjectdetectionKeras/Custom/callbacks.py
ObjectdetectionKeras/Custom/evaluate.py
ObjectdetectionKeras/Custom/gen_anchors.py
ObjectdetectionKeras/Custom/generator.py
ObjectdetectionKeras/Custom/voc.py
ObjectdetectionKeras/Custom/yolo.py
ObjectdetectionKeras/Custom/utils/__init__.py
ObjectdetectionKeras/Custom/utils/bbox.py
ObjectdetectionKeras/Custom/utils/colors.py
ObjectdetectionKeras/Custom/utils/image.py
ObjectdetectionKeras/Custom/utils/multi_gpu_model.py
ObjectdetectionKeras/Custom/utils/utils.py
ObjectdetectionKeras/YOLOv3/__init__.py
ObjectdetectionKeras/YOLOv3/models.py
ObjectdetectionKeras/YOLOv3/utils.py
ObjectdetectionKeras/keras_resnet/__init__.py
ObjectdetectionKeras/keras_resnet/benchmarks/__init__.py
ObjectdetectionKeras/keras_resnet/blocks/_1d.py
ObjectdetectionKeras/keras_resnet/blocks/_2d.py
ObjectdetectionKeras/keras_resnet/blocks/_3d.py
ObjectdetectionKeras/keras_resnet/blocks/__init__.py
ObjectdetectionKeras/keras_resnet/blocks/_time_distributed_2d.py
ObjectdetectionKeras/keras_resnet/classifiers/_2d.py
ObjectdetectionKeras/keras_resnet/classifiers/__init__.py
ObjectdetectionKeras/keras_resnet/layers/__init__.py
ObjectdetectionKeras/keras_resnet/layers/_batch_normalization.py
ObjectdetectionKeras/keras_resnet/models/_2d.py
ObjectdetectionKeras/keras_resnet/models/__init__.py
ObjectdetectionKeras/keras_resnet/models/_time_distributed_2d.py
ObjectdetectionKeras/keras_retinanet/__init__.py
ObjectdetectionKeras/keras_retinanet/initializers.py
ObjectdetectionKeras/keras_retinanet/losses.py
ObjectdetectionKeras/keras_retinanet/backend/__init__.py
ObjectdetectionKeras/keras_retinanet/backend/common.py
ObjectdetectionKeras/keras_retinanet/backend/dynamic.py
ObjectdetectionKeras/keras_retinanet/backend/tensorflow_backend.py
ObjectdetectionKeras/keras_retinanet/callbacks/__init__.py
ObjectdetectionKeras/keras_retinanet/callbacks/coco.py
